{"home_rewardtheauthor.md":"BwNeGsQX","zh_home_q_a.md":"DvWu91NQ","zh_home_aboutdonate.md":"xZ4wYBgb","index.md":"krjmVaaP","zh_home_rewardtheauthor.md":"Cqs-a34b","home_quickstart.md":"vKLNeiyF","home_q_a.md":"CvoUq6X9","home_aboutdonate.md":"B7JoXmXX","home_changelog.md":"fnIZT1GW","zh_home_changelog.md":"B119Vj2M","zh_home_introduction.md":"CdVdbHqB","zh_index.md":"O9Tv9pC4","zh_home_install.md":"CTUdm50w","zh_urls.md":"Qmg1IuGi","zh_home_quickstart.md":"CkSgsZse","zh_home_feature.md":"7CoP2IW6","home_feature.md":"BmNtOCtO","home_install.md":"CEbAkBH0","zh_home_customconfiguration.md":"CzFD9gsc","home_customconfiguration.md":"xFrhyqfM"}
